lib_bme280/__init__.py
lib_bme280/bme280.py
lib_bme280-0.1.0.dist-info/METADATA
lib_bme280-0.1.0.dist-info/WHEEL
lib_bme280-0.1.0.dist-info/top_level.txt
lib_bme280-0.1.0.dist-info/RECORD
